stripzip.py
python_stripzip-2.0.0.dist-info/licenses/LICENCE.md
python_stripzip-2.0.0.dist-info/METADATA
python_stripzip-2.0.0.dist-info/WHEEL
python_stripzip-2.0.0.dist-info/entry_points.txt
python_stripzip-2.0.0.dist-info/top_level.txt
python_stripzip-2.0.0.dist-info/RECORD
